{
  "model": "iTransformer",
  "residual_model": "xgboost",
  "residual.target": "level",
  "residual.feature_policy": {
    "include_base_prediction": true,
    "include_horizon_step": true,
    "include_date_features": false,
    "lag_features": {
      "enabled": true,
      "sources": [
        "y_hat_base"
      ],
      "steps": [
        1,
        2,
        3,
        4,
        6,
        12,
        24
      ],
      "transforms": [
        "raw"
      ]
    },
    "exog_sources": {
      "hist": [
        "Com_Gasoline",
        "Com_LME_Zn_Inv",
        "Com_OrangeJuice",
        "Com_Cheese",
        "Bonds_BRZ_1Y",
        "Idx_OVX",
        "Com_Cu_Gold_Ratio",
        "Com_LME_Sn_Inv",
        "Idx_CSI300",
        "Com_LME_Zn_Spread",
        "Bonds_CHN_Spread_5Y_2Y",
        "Com_LME_Al_Spread",
        "Bonds_CHN_Spread_2Y_1Y",
        "Com_Oil_Spread",
        "Bonds_CHN_Spread_10Y_5Y"
      ],
      "futr": [],
      "static": []
    }
  },
  "active_feature_columns": [
    "horizon_step",
    "y_hat_base"
  ],
  "fold_count": 12,
  "backcast_rows_total": 5616,
  "corrected_eval_rows": 96,
  "corrected_eval_mode": "per_fold_backcast_runtime",
  "tscv_policy": {
    "n_windows": 12,
    "horizon": 8,
    "step_size": 8,
    "gap": 0,
    "max_train_size": null
  },
  "artifact_layout": "residual/<model>/folds/fold_{i:03d}/(backcast_panel.csv, corrected_eval.csv, base_checkpoint/, residual_checkpoint/model.ubj)"
}