{
  "manifest_version": "1",
  "artifact_schema_version": "1",
  "evaluation_protocol_version": "2",
  "config_source_type": "yaml",
  "config_source_path": "/home/sonet/.openclaw/workspace/research/neuralforecast/brentoil-case1_uni.yaml",
  "config_resolved_path": "/home/sonet/.openclaw/workspace/research/neuralforecast/runs/brentoil_case1_re/scheduler/workers/Autoformer/config/config.resolved.json",
  "config_input_sha256": "8299a381135094b1316cd3e43db60533a81b6d2742978fd43415fc3dd04cab9f",
  "config_resolved_sha256": "0422d70a5403ece4378594dd98d18cd9e28f181713729ea3806b3655c5948533",
  "search_space_path": null,
  "search_space_sha256": null,
  "entrypoint_version": "neuralforecast-residual-v1",
  "compat_mode": "dual_read",
  "jobs": [
    {
      "model": "LSTM",
      "requested_mode": "learned_fixed",
      "validated_mode": "learned_fixed",
      "selected_search_params": []
    },
    {
      "model": "NHITS",
      "requested_mode": "learned_fixed",
      "validated_mode": "learned_fixed",
      "selected_search_params": []
    },
    {
      "model": "DLinear",
      "requested_mode": "learned_fixed",
      "validated_mode": "learned_fixed",
      "selected_search_params": []
    },
    {
      "model": "Autoformer",
      "requested_mode": "learned_fixed",
      "validated_mode": "learned_fixed",
      "selected_search_params": []
    },
    {
      "model": "PatchTST",
      "requested_mode": "learned_fixed",
      "validated_mode": "learned_fixed",
      "selected_search_params": []
    },
    {
      "model": "Naive",
      "requested_mode": "baseline_fixed",
      "validated_mode": "baseline_fixed",
      "selected_search_params": []
    }
  ],
  "training_search": {
    "requested_mode": "training_fixed",
    "validated_mode": "training_fixed",
    "selected_search_params": []
  },
  "residual": {
    "model": "xgboost",
    "requested_mode": "residual_disabled",
    "validated_mode": "residual_disabled",
    "selected_search_params": []
  },
  "training": {
    "loss": "mse"
  }
}